.gitignore
LICENSE
MANIFEST.in
README.md
VERSION
setup.py
Chu.egg-info/PKG-INFO
Chu.egg-info/SOURCES.txt
Chu.egg-info/dependency_links.txt
Chu.egg-info/requires.txt
Chu.egg-info/top_level.txt
chu/__init__.py
chu/connection.py
chu/rpc.py
chu/worker.py
chu/examples/simple_rpc.py
chu/tests/__init__.py
chu/tests/rabbit_worker.py
chu/tests/test_rabbit_worker.py
chu/tests/util.py
docs/Makefile
docs/conf.py
docs/connection.rst
docs/index.rst
docs/make.bat
docs/rpc.rst