Metadata-Version: 1.1
Name: Chu
Version: 0.2.0
Summary: Tornado Rabbit clients built on Pika
Home-page: http://github.com/shopwiki/chu
Author: Patrick Lawson
Author-email: plawson@shopwiki.com
License: Apache 2
Platform: UNKNOWN
Classifier: Development Status :: 2 - Pre-Alpha
Classifier: Intended Audience :: Developers
Classifier: License :: OSI Approved :: Apache Software License
Classifier: Operating System :: OS Independent
Classifier: Programming Language :: Python
Classifier: Topic :: Software Development :: Libraries :: Python Modules
